{"name":"calibration_score","description":"\nGet the calibration report — Brier score, accuracy, and\nconfidence-vs-outcome breakdown. Lower Brier score = better calibrated.\n\nPerfect calibration: Brier = 0.0\nRandom guessing: Brier = 0.25\nAlways wrong at 100%: Brier = 1.0\n\nArgs:\n    domain: Filter by domain (empty = all domains)\n    days: Look back period in days\n","parameters":{"properties":{"days":{"default":30,"title":"Days","type":"integer"},"domain":{"default":"","title":"Domain","type":"string"}},"title":"calibration_scoreArguments","type":"object"}}